Metadata-Version: 2.1
Name: datasette-enrichments-ollama
Version: 0.1
Summary: Datasette enrichment for analyzing row data using a locally hosted - or remote - ollama instance
Author: Marcus Davidson
License: Apache-2.0
Project-URL: Homepage, https://github.com/mdav43/datasette-enrichments-ollama
Project-URL: Changelog, https://github.com/mdav43/datasette-enrichments-ollama/releases
Project-URL: Issues, https://github.com/mdav43/datasette-enrichments-ollama/issues
Project-URL: CI, https://github.com/mdav43/datasette-enrichments-ollama/actions
Classifier: Framework :: Datasette
Classifier: License :: OSI Approved :: Apache Software License
Requires-Python: >=3.8
License-File: LICENSE
Requires-Dist: datasette-enrichments >=0.2
Requires-Dist: sqlite-utils
Provides-Extra: test
Requires-Dist: pytest ; extra == 'test'
Requires-Dist: pytest-asyncio ; extra == 'test'
